nistauthenticator/__init__.py
nistauthenticator/nistauthenticator.py
nistauthenticator-0.1.0.dist-info/LICENSE
nistauthenticator-0.1.0.dist-info/METADATA
nistauthenticator-0.1.0.dist-info/WHEEL
nistauthenticator-0.1.0.dist-info/top_level.txt
nistauthenticator-0.1.0.dist-info/RECORD
