Metadata-Version: 2.1
Name: nistauthenticator
Version: 0.1.0
Summary: A HTTP header based authenticator for JupyterHub
Home-page: https://github.com/yunlanli/nistauthenticator
Author: Yunlan Li
Author-email: yl4387@columbia.edu
License: https://mit-license.org/
Keywords: JupyterHub,HTTP header,Authenticator
Platform: UNKNOWN
Requires-Python: >=3.6
License-File: LICENSE
Requires-Dist: jupyterhub
